somenergia_apinergia/__init__.py
somenergia_apinergia/apinergia.py
somenergia_apinergia_client-0.0.1.dist-info/LICENSE
somenergia_apinergia_client-0.0.1.dist-info/METADATA
somenergia_apinergia_client-0.0.1.dist-info/WHEEL
somenergia_apinergia_client-0.0.1.dist-info/top_level.txt
somenergia_apinergia_client-0.0.1.dist-info/RECORD
