Metadata-Version: 2.1
Name: somenergia-apinergia-client
Version: 0.0.1
Summary: SomEnergia Apinergia API Wrapper
Home-page: https://github.com/Som-Energia/somenergia-apinergia-client
Author: Pol Monsó Purtí
Author-email: itcrowd@somenergia.coop
Project-URL: Bug Tracker, https://github.com/Som-Energia/somenergia-apinergia-client/issues
Classifier: Programming Language :: Python :: 3
Classifier: License :: OSI Approved :: GNU General Public License v3 or later (GPLv3+)
Classifier: Operating System :: OS Independent
Requires-Python: >=3.6
License-File: LICENSE
Requires-Dist: pandas
Requires-Dist: python-dotenv
Provides-Extra: dev
Requires-Dist: black ; extra == 'dev'
Requires-Dist: pytest ; extra == 'dev'
